hippius_sdk/__init__.py
hippius_sdk/api_client.py
hippius_sdk/cli.py
hippius_sdk/cli_assets.py
hippius_sdk/cli_handlers.py
hippius_sdk/cli_parser.py
hippius_sdk/cli_rich.py
hippius_sdk/client.py
hippius_sdk/config.py
hippius_sdk/db/README.md
hippius_sdk/db/env.db.template
hippius_sdk/db/migrations/20241201000001_create_key_storage_tables.sql
hippius_sdk/db/migrations/20241202000001_switch_to_subaccount_encryption.sql
hippius_sdk/db/setup_database.sh
hippius_sdk/db_utils.py
hippius_sdk/erasure_coding.py
hippius_sdk/errors.py
hippius_sdk/incentives.py
hippius_sdk/ipfs.py
hippius_sdk/ipfs_core.py
hippius_sdk/key_storage.py
hippius_sdk/substrate.py
hippius_sdk/utils.py
hippius-0.2.74.dist-info/METADATA
hippius-0.2.74.dist-info/WHEEL
hippius-0.2.74.dist-info/entry_points.txt
hippius-0.2.74.dist-info/RECORD
