Metadata-Version: 2.1
Name: hippius
Version: 0.2.74
Summary: Python SDK and CLI for Hippius blockchain storage
Home-page: https://github.com/thenervelab/hippius-sdk
Author: Dubs
Author-email: dubs@dubs.rs
Requires-Python: >=3.10,<3.14
Classifier: Development Status :: 3 - Alpha
Classifier: Intended Audience :: Developers
Classifier: License :: OSI Approved :: MIT License
Classifier: Programming Language :: Python :: 3
Classifier: Programming Language :: Python :: 3.10
Classifier: Programming Language :: Python :: 3.11
Classifier: Programming Language :: Python :: 3.9
Provides-Extra: clipboard
Provides-Extra: key-storage
Requires-Dist: asyncpg (>=0.29.0,<0.30.0) ; extra == "key-storage"
Requires-Dist: base58 (>=2.1.1,<3.0.0)
Requires-Dist: cryptography (>=44.0.0,<45.0.0)
Requires-Dist: httpx (>=0.28.1,<0.29.0)
Requires-Dist: mnemonic (>=0.20,<0.21)
Requires-Dist: pandas (>=2.2.3,<3.0.0)
Requires-Dist: pyarrow (>=19.0.0,<20.0.0)
Requires-Dist: pydantic (>=2.0.0,<3.0.0)
Requires-Dist: pynacl (>=1.5.0,<2.0.0)
Requires-Dist: pyperclip (>=1.8.2,<2.0.0) ; extra == "clipboard"
Requires-Dist: python-dotenv (>=1.0.0,<2.0.0)
Requires-Dist: requests (>=2.28.1,<3.0.0)
Requires-Dist: rich (>=14.0.0,<15.0.0)
Requires-Dist: substrate-interface (==1.7.11)
Requires-Dist: zfec (>=1.5.3,<2.0.0)
Project-URL: Documentation, https://github.com/thenervelab/hippius-sdk/docs
Project-URL: Repository, https://github.com/thenervelab/hippius-sdk
